Metadata-Version: 1.0
Name: django-admin-action-buttons
Version: 0.1.9
Summary: Django admin tweak that replaces list action dropdown with buttons
Home-page: https://github.com/frnhr/django-admin-action-buttons
Author: Fran Hrzenjak
Author-email: fran@changeset.hr
License: MIT
Platform: UNKNOWN
